make_excel.py
make_excel-1.2.0.dev1.dist-info/RECORD
make_excel-1.2.0.dev1.dist-info/METADATA
make_excel-1.2.0.dev1.dist-info/entry_points.txt
make_excel-1.2.0.dev1.dist-info/WHEEL
make_excel-1.2.0.dev1.dist-info/DESCRIPTION.rst
make_excel-1.2.0.dev1.dist-info/top_level.txt
make_excel-1.2.0.dev1.dist-info/metadata.json
make_excel-1.2.0.dev1.dist-info/pbr.json
