Metadata-Version: 2.0
Name: make-excel
Version: 1.2.0.dev1
Summary: Create .xls file with Python dictionary
Home-page: https://github.com/nidhinbose89/make_excel.git
Author: Nidhin Bose J
Author-email: nidhinb@yahoo.com
License: MIT
Keywords: Create .xls file with Python dictionary
Platform: UNKNOWN
Classifier: Development Status :: 3 - Alpha
Classifier: Intended Audience :: Developers
Classifier: Topic :: Software Development :: Build Tools
Classifier: License :: OSI Approved :: MIT License
Classifier: Programming Language :: Python :: 2.7
Requires-Dist: xlwt
Requires-Dist: xlrd
Requires-Dist: xlutils
